synesthesiaer/__init__.py
synesthesiaer/main.py
synesthesiaer-0.1.0.dist-info/LICENSE
synesthesiaer-0.1.0.dist-info/METADATA
synesthesiaer-0.1.0.dist-info/WHEEL
synesthesiaer-0.1.0.dist-info/top_level.txt
synesthesiaer-0.1.0.dist-info/RECORD
