Metadata-Version: 2.1
Name: synesthesiaer
Version: 0.1.0
Summary: Assigns light and sound frequencies to prime numbers and mixes them using pygame.
Author-email: Jackson Walters <jacksonwalters@gmail.com>
Project-URL: Homepage, https://github.com/jacksonwalters/synesthesiaer
Project-URL: Bug Tracker, https://github.com/pypa/synesthesiaer/issues
Classifier: Programming Language :: Python :: 3
Classifier: License :: OSI Approved :: MIT License
Classifier: Operating System :: OS Independent
Requires-Python: >=3.7
License-File: LICENSE
